[
  {
    "name":"Absorb",
    "type":"Grass",
    "cat":"Special",
    "power":20,
    "acc":100,
    "pp":25,
    "effect":"User recovers half the HP inflicted on opponent."
  },
  {
    "name":"Acid",
    "type":"Poison",
    "cat":"Special",
    "power":40,
    "acc":100,
    "pp":30,
    "effect":"May lower opponent's Special Defense."
  },
  {
    "name":"Acid Armor",
    "type":"Poison",
    "cat":"Status",
    "power":null,
    "acc":null,
    "pp":20,
    "effect":"Sharply raises user's Defense."
  },
  {
    "name":"Agility",
    "type":"Psychic",
    "cat":"Status",
    "power":null,
    "acc":null,
    "pp":30,
    "effect":"Sharply raises user's Speed."
  },
  {
    "name":"Amnesia",
    "type":"Psychic",
    "cat":"Status",
    "power":null,
    "acc":null,
    "pp":20,
    "effect":"Sharply raises user's Special Defense."
  },
  {
    "name":"Aurora Beam",
    "type":"Ice",
    "cat":"Special",
    "power":65,
    "acc":100,
    "pp":20,
    "effect":"May lower opponent's Attack."
  },
  {
    "name":"Barrage",
    "type":"Normal",
    "cat":"Physical",
    "power":15,
    "acc":85,
    "pp":20,
    "effect":"Hits 2-5 times in one turn."
  },
  {
    "name":"Barrier",
    "type":"Psychic",
    "cat":"Status",
    "power":null,
    "acc":null,
    "pp":20,
    "effect":"Sharply raises user's Defense."
  },
  {
    "name":"Bide",
    "type":"Normal",
    "cat":"Physical",
    "power":null,
    "acc":null,
    "pp":10,
    "effect":"User takes damage for two turns then strikes back double."
  },
  {
    "name":"Bind",
    "type":"Normal",
    "cat":"Physical",
    "power":15,
    "acc":85,
    "pp":20,
    "effect":"Traps opponent, damaging them for 4-5 turns."
  },
  {
    "name":"Bite",
    "type":"Dark",
    "cat":"Physical",
    "power":60,
    "acc":100,
    "pp":25,
    "effect":"May cause flinching."
  },
  {
    "name":"Blizzard",
    "type":"Ice",
    "cat":"Special",
    "power":110,
    "acc":70,
    "pp":5,
    "effect":"May freeze opponent."
  },
  {
    "name":"Body Slam",
    "type":"Normal",
    "cat":"Physical",
    "power":85,
    "acc":100,
    "pp":15,
    "effect":"May paralyze opponent."
  },
  {
    "name":"Bone Club",
    "type":"Ground",
    "cat":"Physical",
    "power":65,
    "acc":85,
    "pp":20,
    "effect":"May cause flinching."
  },
  {
    "name":"Bonemerang",
    "type":"Ground",
    "cat":"Physical",
    "power":50,
    "acc":90,
    "pp":10,
    "effect":"Hits twice in one turn."
  },
  {
    "name":"Bubble",
    "type":"Water",
    "cat":"Special",
    "power":40,
    "acc":100,
    "pp":30,
    "effect":"May lower opponent's Speed."
  },
  {
    "name":"Bubble Beam",
    "type":"Water",
    "cat":"Special",
    "power":65,
    "acc":100,
    "pp":20,
    "effect":"May lower opponent's Speed."
  },
  {
    "name":"Clamp",
    "type":"Water",
    "cat":"Physical",
    "power":35,
    "acc":85,
    "pp":10,
    "effect":"Traps opponent, damaging them for 4-5 turns."
  },
  {
    "name":"Comet Punch",
    "type":"Normal",
    "cat":"Physical",
    "power":18,
    "acc":85,
    "pp":15,
    "effect":"Hits 2-5 times in one turn."
  },
  {
    "name":"Confuse Ray",
    "type":"Ghost",
    "cat":"Status",
    "power":null,
    "acc":100,
    "pp":10,
    "effect":"Confuses opponent."
  },
  {
    "name":"Confusion",
    "type":"Psychic",
    "cat":"Special",
    "power":50,
    "acc":100,
    "pp":25,
    "effect":"May confuse opponent."
  },
  {
    "name":"Constrict",
    "type":"Normal",
    "cat":"Physical",
    "power":10,
    "acc":100,
    "pp":35,
    "effect":"May lower opponent's Speed by one stage."
  },
  {
    "name":"Conversion",
    "type":"Normal",
    "cat":"Status",
    "power":null,
    "acc":null,
    "pp":30,
    "effect":"Changes user's type to that of its first move."
  },
  {
    "name":"Counter",
    "type":"Fighting",
    "cat":"Physical",
    "power":null,
    "acc":100,
    "pp":20,
    "effect":"When hit by a Physical Attack, user strikes back with 2x power."
  },
  {
    "name":"Crabhammer",
    "type":"Water",
    "cat":"Physical",
    "power":100,
    "acc":90,
    "pp":10,
    "effect":"High critical hit ratio."
  },
  {
    "name":"Cut",
    "type":"Normal",
    "cat":"Physical",
    "power":50,
    "acc":95,
    "pp":30,
    "effect":""
  },
  {
    "name":"Defense Curl",
    "type":"Normal",
    "cat":"Status",
    "power":null,
    "acc":null,
    "pp":40,
    "effect":"Raises user's Defense."
  },
  {
    "name":"Dig",
    "type":"Ground",
    "cat":"Physical",
    "power":80,
    "acc":100,
    "pp":10,
    "effect":"Digs underground on first turn, attacks on second. Can also escape from\n caves."
  },
  {
    "name":"Disable",
    "type":"Normal",
    "cat":"Status",
    "power":null,
    "acc":100,
    "pp":20,
    "effect":"Opponent can't use its last attack for a few turns."
  },
  {
    "name":"Dizzy Punch",
    "type":"Normal",
    "cat":"Physical",
    "power":70,
    "acc":100,
    "pp":10,
    "effect":"May confuse opponent."
  },
  {
    "name":"Double Kick",
    "type":"Fighting",
    "cat":"Physical",
    "power":30,
    "acc":100,
    "pp":30,
    "effect":"Hits twice in one turn."
  },
  {
    "name":"Double Slap",
    "type":"Normal",
    "cat":"Physical",
    "power":15,
    "acc":85,
    "pp":10,
    "effect":"Hits 2-5 times in one turn."
  },
  {
    "name":"Double Team",
    "type":"Normal",
    "cat":"Status",
    "power":null,
    "acc":null,
    "pp":15,
    "effect":"Raises user's Evasiveness."
  },
  {
    "name":"Double-Edge",
    "type":"Normal",
    "cat":"Physical",
    "power":120,
    "acc":100,
    "pp":15,
    "effect":"User receives recoil damage."
  },
  {
    "name":"Dragon Rage",
    "type":"Dragon",
    "cat":"Special",
    "power":null,
    "acc":100,
    "pp":10,
    "effect":"Always inflicts 40 HP."
  },
  {
    "name":"Dream Eater",
    "type":"Psychic",
    "cat":"Special",
    "power":100,
    "acc":100,
    "pp":15,
    "effect":"User recovers half the HP inflicted on a sleeping opponent."
  },
  {
    "name":"Drill Peck",
    "type":"Flying",
    "cat":"Physical",
    "power":80,
    "acc":100,
    "pp":20,
    "effect":""
  },
  {
    "name":"Earthquake",
    "type":"Ground",
    "cat":"Physical",
    "power":100,
    "acc":100,
    "pp":10,
    "effect":"Power is doubled if opponent is underground from using Dig."
  },
  {
    "name":"Egg Bomb",
    "type":"Normal",
    "cat":"Physical",
    "power":100,
    "acc":75,
    "pp":10,
    "effect":""
  },
  {
    "name":"Ember",
    "type":"Fire",
    "cat":"Special",
    "power":40,
    "acc":100,
    "pp":25,
    "effect":"May burn opponent."
  },
  {
    "name":"Explosion",
    "type":"Normal",
    "cat":"Physical",
    "power":250,
    "acc":100,
    "pp":5,
    "effect":"User faints."
  },
  {
    "name":"Fire Blast",
    "type":"Fire",
    "cat":"Special",
    "power":110,
    "acc":85,
    "pp":5,
    "effect":"May burn opponent."
  },
  {
    "name":"Fire Punch",
    "type":"Fire",
    "cat":"Physical",
    "power":75,
    "acc":100,
    "pp":15,
    "effect":"May burn opponent."
  },
  {
    "name":"Fire Spin",
    "type":"Fire",
    "cat":"Special",
    "power":35,
    "acc":85,
    "pp":15,
    "effect":"Traps opponent, damaging them for 4-5 turns."
  },
  {
    "name":"Fissure",
    "type":"Ground",
    "cat":"Physical",
    "power":null,
    "acc":null,
    "pp":5,
    "effect":"One-Hit-KO, if it hits."
  },
  {
    "name":"Flamethrower",
    "type":"Fire",
    "cat":"Special",
    "power":90,
    "acc":100,
    "pp":15,
    "effect":"May burn opponent."
  },
  {
    "name":"Flash",
    "type":"Normal",
    "cat":"Status",
    "power":null,
    "acc":100,
    "pp":20,
    "effect":"Lowers opponent's Accuracy."
  },
  {
    "name":"Fly",
    "type":"Flying",
    "cat":"Physical",
    "power":90,
    "acc":95,
    "pp":15,
    "effect":"Flies up on first turn, attacks on second turn."
  },
  {
    "name":"Focus Energy",
    "type":"Normal",
    "cat":"Status",
    "power":null,
    "acc":null,
    "pp":30,
    "effect":"Increases critical hit ratio."
  },
  {
    "name":"Fury Attack",
    "type":"Normal",
    "cat":"Physical",
    "power":15,
    "acc":85,
    "pp":20,
    "effect":"Hits 2-5 times in one turn."
  },
  {
    "name":"Fury Swipes",
    "type":"Normal",
    "cat":"Physical",
    "power":18,
    "acc":80,
    "pp":15,
    "effect":"Hits 2-5 times in one turn."
  },
  {
    "name":"Glare",
    "type":"Normal",
    "cat":"Status",
    "power":null,
    "acc":100,
    "pp":30,
    "effect":"Paralyzes opponent."
  },
  {
    "name":"Growl",
    "type":"Normal",
    "cat":"Status",
    "power":null,
    "acc":100,
    "pp":40,
    "effect":"Lowers opponent's Attack."
  },
  {
    "name":"Growth",
    "type":"Normal",
    "cat":"Status",
    "power":null,
    "acc":null,
    "pp":40,
    "effect":"Raises user's Attack and Special Attack."
  },
  {
    "name":"Guillotine",
    "type":"Normal",
    "cat":"Physical",
    "power":null,
    "acc":null,
    "pp":5,
    "effect":"One-Hit-KO, if it hits."
  },
  {
    "name":"Gust",
    "type":"Flying",
    "cat":"Special",
    "power":40,
    "acc":100,
    "pp":35,
    "effect":"Hits Pokémon using Fly/Bounce with double power."
  },
  {
    "name":"Harden",
    "type":"Normal",
    "cat":"Status",
    "power":null,
    "acc":null,
    "pp":30,
    "effect":"Raises user's Defense."
  },
  {
    "name":"Haze",
    "type":"Ice",
    "cat":"Status",
    "power":null,
    "acc":null,
    "pp":30,
    "effect":"Resets all stat changes."
  },
  {
    "name":"Headbutt",
    "type":"Normal",
    "cat":"Physical",
    "power":70,
    "acc":100,
    "pp":15,
    "effect":"May cause flinching."
  },
  {
    "name":"High Jump Kick",
    "type":"Fighting",
    "cat":"Physical",
    "power":130,
    "acc":90,
    "pp":10,
    "effect":"If it misses, the user loses half their HP."
  },
  {
    "name":"Horn Attack",
    "type":"Normal",
    "cat":"Physical",
    "power":65,
    "acc":100,
    "pp":25,
    "effect":""
  },
  {
    "name":"Horn Drill",
    "type":"Normal",
    "cat":"Physical",
    "power":null,
    "acc":null,
    "pp":5,
    "effect":"One-Hit-KO, if it hits."
  },
  {
    "name":"Hydro Pump",
    "type":"Water",
    "cat":"Special",
    "power":110,
    "acc":80,
    "pp":5,
    "effect":""
  },
  {
    "name":"Hyper Beam",
    "type":"Normal",
    "cat":"Special",
    "power":150,
    "acc":90,
    "pp":5,
    "effect":"User must recharge next turn."
  },
  {
    "name":"Hyper Fang",
    "type":"Normal",
    "cat":"Physical",
    "power":80,
    "acc":90,
    "pp":15,
    "effect":"May cause flinching."
  },
  {
    "name":"Hypnosis",
    "type":"Psychic",
    "cat":"Status",
    "power":null,
    "acc":60,
    "pp":20,
    "effect":"Puts opponent to sleep."
  },
  {
    "name":"Ice Beam",
    "type":"Ice",
    "cat":"Special",
    "power":90,
    "acc":100,
    "pp":10,
    "effect":"May freeze opponent."
  },
  {
    "name":"Ice Punch",
    "type":"Ice",
    "cat":"Physical",
    "power":75,
    "acc":100,
    "pp":15,
    "effect":"May freeze opponent."
  },
  {
    "name":"Jump Kick",
    "type":"Fighting",
    "cat":"Physical",
    "power":100,
    "acc":95,
    "pp":10,
    "effect":"If it misses, the user loses half their HP."
  },
  {
    "name":"Karate Chop",
    "type":"Fighting",
    "cat":"Physical",
    "power":50,
    "acc":100,
    "pp":25,
    "effect":"High critical hit ratio."
  },
  {
    "name":"Kinesis",
    "type":"Psychic",
    "cat":"Status",
    "power":null,
    "acc":80,
    "pp":15,
    "effect":"Lowers opponent's Accuracy."
  },
  {
    "name":"Leech Life",
    "type":"Bug",
    "cat":"Physical",
    "power":20,
    "acc":100,
    "pp":15,
    "effect":"User recovers half the HP inflicted on opponent."
  },
  {
    "name":"Leech Seed",
    "type":"Grass",
    "cat":"Status",
    "power":null,
    "acc":90,
    "pp":10,
    "effect":"User steals HP from opponent each turn."
  },
  {
    "name":"Leer",
    "type":"Normal",
    "cat":"Status",
    "power":null,
    "acc":100,
    "pp":30,
    "effect":"Lowers opponent's Defense."
  },
  {
    "name":"Lick",
    "type":"Ghost",
    "cat":"Physical",
    "power":30,
    "acc":100,
    "pp":30,
    "effect":"May paralyze opponent."
  },
  {
    "name":"Light Screen",
    "type":"Psychic",
    "cat":"Status",
    "power":null,
    "acc":null,
    "pp":30,
    "effect":"Halves damage from Special attacks for 5 turns."
  },
  {
    "name":"Lovely Kiss",
    "type":"Normal",
    "cat":"Status",
    "power":null,
    "acc":75,
    "pp":10,
    "effect":"Puts opponent to sleep."
  },
  {
    "name":"Low Kick",
    "type":"Fighting",
    "cat":"Physical",
    "power":null,
    "acc":100,
    "pp":20,
    "effect":"The heavier the opponent, the stronger the attack."
  },
  {
    "name":"Meditate",
    "type":"Psychic",
    "cat":"Status",
    "power":null,
    "acc":null,
    "pp":40,
    "effect":"Raises user's Attack."
  },
  {
    "name":"Mega Drain",
    "type":"Grass",
    "cat":"Special",
    "power":40,
    "acc":100,
    "pp":15,
    "effect":"User recovers half the HP inflicted on opponent."
  },
  {
    "name":"Mega Kick",
    "type":"Normal",
    "cat":"Physical",
    "power":120,
    "acc":75,
    "pp":5,
    "effect":""
  },
  {
    "name":"Mega Punch",
    "type":"Normal",
    "cat":"Physical",
    "power":80,
    "acc":85,
    "pp":20,
    "effect":""
  },
  {
    "name":"Metronome",
    "type":"Normal",
    "cat":"Status",
    "power":null,
    "acc":null,
    "pp":10,
    "effect":"User performs any move in the game at random."
  },
  {
    "name":"Mimic",
    "type":"Normal",
    "cat":"Status",
    "power":null,
    "acc":null,
    "pp":10,
    "effect":"Copies the opponent's last move."
  },
  {
    "name":"Minimize",
    "type":"Normal",
    "cat":"Status",
    "power":null,
    "acc":null,
    "pp":10,
    "effect":"Sharply raises user's Evasiveness."
  },
  {
    "name":"Mirror Move",
    "type":"Flying",
    "cat":"Status",
    "power":null,
    "acc":null,
    "pp":20,
    "effect":"User performs the opponent's last move."
  },
  {
    "name":"Mist",
    "type":"Ice",
    "cat":"Status",
    "power":null,
    "acc":null,
    "pp":30,
    "effect":"User's stats cannot be changed for a period of time."
  },
  {
    "name":"Night Shade",
    "type":"Ghost",
    "cat":"Special",
    "power":null,
    "acc":100,
    "pp":15,
    "effect":"Inflicts damage equal to user's level."
  },
  {
    "name":"Pay Day",
    "type":"Normal",
    "cat":"Physical",
    "power":40,
    "acc":100,
    "pp":20,
    "effect":"A small amount of money is gained after the battle resolves."
  },
  {
    "name":"Peck",
    "type":"Flying",
    "cat":"Physical",
    "power":35,
    "acc":100,
    "pp":35,
    "effect":""
  },
  {
    "name":"Petal Dance",
    "type":"Grass",
    "cat":"Special",
    "power":120,
    "acc":100,
    "pp":10,
    "effect":"User attacks for 2-3 turns but then becomes confused."
  },
  {
    "name":"Pin Missile",
    "type":"Bug",
    "cat":"Physical",
    "power":25,
    "acc":95,
    "pp":20,
    "effect":"Hits 2-5 times in one turn."
  },
  {
    "name":"Poison Gas",
    "type":"Poison",
    "cat":"Status",
    "power":null,
    "acc":90,
    "pp":40,
    "effect":"Poisons opponent."
  },
  {
    "name":"Poison Powder",
    "type":"Poison",
    "cat":"Status",
    "power":null,
    "acc":75,
    "pp":35,
    "effect":"Poisons opponent."
  },
  {
    "name":"Poison Sting",
    "type":"Poison",
    "cat":"Physical",
    "power":15,
    "acc":100,
    "pp":35,
    "effect":"May poison the opponent."
  },
  {
    "name":"Pound",
    "type":"Normal",
    "cat":"Physical",
    "power":40,
    "acc":100,
    "pp":35,
    "effect":""
  },
  {
    "name":"Psybeam",
    "type":"Psychic",
    "cat":"Special",
    "power":65,
    "acc":100,
    "pp":20,
    "effect":"May confuse opponent."
  },
  {
    "name":"Psychic",
    "type":"Psychic",
    "cat":"Special",
    "power":90,
    "acc":100,
    "pp":10,
    "effect":"May lower opponent's Special Defense."
  },
  {
    "name":"Psywave",
    "type":"Psychic",
    "cat":"Special",
    "power":null,
    "acc":80,
    "pp":15,
    "effect":"Inflicts damage 50-150% of user's level."
  },
  {
    "name":"Quick Attack",
    "type":"Normal",
    "cat":"Physical",
    "power":40,
    "acc":100,
    "pp":30,
    "effect":"User attacks first."
  },
  {
    "name":"Rage",
    "type":"Normal",
    "cat":"Physical",
    "power":20,
    "acc":100,
    "pp":20,
    "effect":"Raises user's Attack when hit."
  },
  {
    "name":"Razor Leaf",
    "type":"Grass",
    "cat":"Physical",
    "power":55,
    "acc":95,
    "pp":25,
    "effect":"High critical hit ratio."
  },
  {
    "name":"Razor Wind",
    "type":"Normal",
    "cat":"Special",
    "power":80,
    "acc":100,
    "pp":10,
    "effect":"Charges on first turn, attacks on second. High critical hit ratio."
  },
  {
    "name":"Recover",
    "type":"Normal",
    "cat":"Status",
    "power":null,
    "acc":null,
    "pp":10,
    "effect":"User recovers half its max HP."
  },
  {
    "name":"Reflect",
    "type":"Psychic",
    "cat":"Status",
    "power":null,
    "acc":null,
    "pp":20,
    "effect":"Halves damage from Physical attacks for 5 turns."
  },
  {
    "name":"Rest",
    "type":"Psychic",
    "cat":"Status",
    "power":null,
    "acc":null,
    "pp":10,
    "effect":"User sleeps for 2 turns, but user is fully healed."
  },
  {
    "name":"Roar",
    "type":"Normal",
    "cat":"Status",
    "power":null,
    "acc":null,
    "pp":20,
    "effect":"In battles, the opponent switches. In the wild, the Pokémon runs."
  },
  {
    "name":"Rock Slide",
    "type":"Rock",
    "cat":"Physical",
    "power":75,
    "acc":90,
    "pp":10,
    "effect":"May cause flinching."
  },
  {
    "name":"Rock Throw",
    "type":"Rock",
    "cat":"Physical",
    "power":50,
    "acc":90,
    "pp":15,
    "effect":""
  },
  {
    "name":"Rolling Kick",
    "type":"Fighting",
    "cat":"Physical",
    "power":60,
    "acc":85,
    "pp":15,
    "effect":"May cause flinching."
  },
  {
    "name":"Sand Attack",
    "type":"Ground",
    "cat":"Status",
    "power":null,
    "acc":100,
    "pp":15,
    "effect":"Lowers opponent's Accuracy."
  },
  {
    "name":"Scratch",
    "type":"Normal",
    "cat":"Physical",
    "power":40,
    "acc":100,
    "pp":35,
    "effect":""
  },
  {
    "name":"Screech",
    "type":"Normal",
    "cat":"Status",
    "power":null,
    "acc":85,
    "pp":40,
    "effect":"Sharply lowers opponent's Defense."
  },
  {
    "name":"Seismic Toss",
    "type":"Fighting",
    "cat":"Physical",
    "power":null,
    "acc":100,
    "pp":20,
    "effect":"Inflicts damage equal to user's level."
  },
  {
    "name":"Self-Destruct",
    "type":"Normal",
    "cat":"Physical",
    "power":200,
    "acc":100,
    "pp":5,
    "effect":"User faints."
  },
  {
    "name":"Sharpen",
    "type":"Normal",
    "cat":"Status",
    "power":null,
    "acc":null,
    "pp":30,
    "effect":"Raises user's Attack."
  },
  {
    "name":"Sing",
    "type":"Normal",
    "cat":"Status",
    "power":null,
    "acc":55,
    "pp":15,
    "effect":"Puts opponent to sleep."
  },
  {
    "name":"Skull Bash",
    "type":"Normal",
    "cat":"Physical",
    "power":130,
    "acc":100,
    "pp":10,
    "effect":"Raises Defense on first turn, attacks on second."
  },
  {
    "name":"Sky Attack",
    "type":"Flying",
    "cat":"Physical",
    "power":140,
    "acc":90,
    "pp":5,
    "effect":"Charges on first turn, attacks on second. May cause flinching."
  },
  {
    "name":"Slam",
    "type":"Normal",
    "cat":"Physical",
    "power":80,
    "acc":75,
    "pp":20,
    "effect":""
  },
  {
    "name":"Slash",
    "type":"Normal",
    "cat":"Physical",
    "power":70,
    "acc":100,
    "pp":20,
    "effect":"High critical hit ratio."
  },
  {
    "name":"Sleep Powder",
    "type":"Grass",
    "cat":"Status",
    "power":null,
    "acc":75,
    "pp":15,
    "effect":"Puts opponent to sleep."
  },
  {
    "name":"Sludge",
    "type":"Poison",
    "cat":"Special",
    "power":65,
    "acc":100,
    "pp":20,
    "effect":"May poison opponent."
  },
  {
    "name":"Smog",
    "type":"Poison",
    "cat":"Special",
    "power":30,
    "acc":70,
    "pp":20,
    "effect":"May poison opponent."
  },
  {
    "name":"Smokescreen",
    "type":"Normal",
    "cat":"Status",
    "power":null,
    "acc":100,
    "pp":20,
    "effect":"Lowers opponent's Accuracy."
  },
  {
    "name":"Soft-Boiled",
    "type":"Normal",
    "cat":"Status",
    "power":null,
    "acc":null,
    "pp":10,
    "effect":"User recovers half its max HP."
  },
  {
    "name":"Solar Beam",
    "type":"Grass",
    "cat":"Special",
    "power":120,
    "acc":100,
    "pp":10,
    "effect":"Charges on first turn, attacks on second."
  },
  {
    "name":"Sonic Boom",
    "type":"Normal",
    "cat":"Special",
    "power":null,
    "acc":90,
    "pp":20,
    "effect":"Always inflicts 20 HP."
  },
  {
    "name":"Spike Cannon",
    "type":"Normal",
    "cat":"Physical",
    "power":20,
    "acc":100,
    "pp":15,
    "effect":"Hits 2-5 times in one turn."
  },
  {
    "name":"Splash",
    "type":"Normal",
    "cat":"Status",
    "power":null,
    "acc":null,
    "pp":40,
    "effect":"Doesn't do ANYTHING."
  },
  {
    "name":"Spore",
    "type":"Grass",
    "cat":"Status",
    "power":null,
    "acc":100,
    "pp":15,
    "effect":"Puts opponent to sleep."
  },
  {
    "name":"Stomp",
    "type":"Normal",
    "cat":"Physical",
    "power":65,
    "acc":100,
    "pp":20,
    "effect":"May cause flinching."
  },
  {
    "name":"Strength",
    "type":"Normal",
    "cat":"Physical",
    "power":80,
    "acc":100,
    "pp":15,
    "effect":""
  },
  {
    "name":"String Shot",
    "type":"Bug",
    "cat":"Status",
    "power":null,
    "acc":95,
    "pp":40,
    "effect":"Sharply lowers opponent's Speed."
  },
  {
    "name":"Struggle",
    "type":"Normal",
    "cat":"Physical",
    "power":50,
    "acc":100,
    "pp":null,
    "effect":"Only usable when all PP are gone. Hurts the user."
  },
  {
    "name":"Stun Spore",
    "type":"Grass",
    "cat":"Status",
    "power":null,
    "acc":75,
    "pp":30,
    "effect":"Paralyzes opponent."
  },
  {
    "name":"Submission",
    "type":"Fighting",
    "cat":"Physical",
    "power":80,
    "acc":80,
    "pp":25,
    "effect":"User receives recoil damage."
  },
  {
    "name":"Substitute",
    "type":"Normal",
    "cat":"Status",
    "power":null,
    "acc":null,
    "pp":10,
    "effect":"Uses HP to creates a decoy that takes hits."
  },
  {
    "name":"Super Fang",
    "type":"Normal",
    "cat":"Physical",
    "power":null,
    "acc":90,
    "pp":10,
    "effect":"Always takes off half of the opponent's HP."
  },
  {
    "name":"Supersonic",
    "type":"Normal",
    "cat":"Status",
    "power":null,
    "acc":55,
    "pp":20,
    "effect":"Confuses opponent."
  },
  {
    "name":"Surf",
    "type":"Water",
    "cat":"Special",
    "power":90,
    "acc":100,
    "pp":15,
    "effect":"Hits all adjacent Pokémon."
  },
  {
    "name":"Swift",
    "type":"Normal",
    "cat":"Special",
    "power":60,
    "acc":null,
    "pp":20,
    "effect":"Ignores Accuracy and Evasiveness."
  },
  {
    "name":"Swords Dance",
    "type":"Normal",
    "cat":"Status",
    "power":null,
    "acc":null,
    "pp":20,
    "effect":"Sharply raises user's Attack."
  },
  {
    "name":"Tackle",
    "type":"Normal",
    "cat":"Physical",
    "power":50,
    "acc":100,
    "pp":35,
    "effect":""
  },
  {
    "name":"Tail Whip",
    "type":"Normal",
    "cat":"Status",
    "power":null,
    "acc":100,
    "pp":30,
    "effect":"Lowers opponent's Defense."
  },
  {
    "name":"Take Down",
    "type":"Normal",
    "cat":"Physical",
    "power":90,
    "acc":85,
    "pp":20,
    "effect":"User receives recoil damage."
  },
  {
    "name":"Teleport",
    "type":"Psychic",
    "cat":"Status",
    "power":null,
    "acc":null,
    "pp":20,
    "effect":"Allows user to flee wild battles; also warps player to last PokéCenter."
  },
  {
    "name":"Thrash",
    "type":"Normal",
    "cat":"Physical",
    "power":120,
    "acc":100,
    "pp":10,
    "effect":"User attacks for 2-3 turns but then becomes confused."
  },
  {
    "name":"Thunder",
    "type":"Electric",
    "cat":"Special",
    "power":110,
    "acc":70,
    "pp":10,
    "effect":"May paralyze opponent."
  },
  {
    "name":"Thunder Punch",
    "type":"Electric",
    "cat":"Physical",
    "power":75,
    "acc":100,
    "pp":15,
    "effect":"May paralyze opponent."
  },
  {
    "name":"Thunder Shock",
    "type":"Electric",
    "cat":"Special",
    "power":40,
    "acc":100,
    "pp":30,
    "effect":"May paralyze opponent."
  },
  {
    "name":"Thunder Wave",
    "type":"Electric",
    "cat":"Status",
    "power":null,
    "acc":100,
    "pp":20,
    "effect":"Paralyzes opponent."
  },
  {
    "name":"Thunderbolt",
    "type":"Electric",
    "cat":"Special",
    "power":90,
    "acc":100,
    "pp":15,
    "effect":"May paralyze opponent."
  },
  {
    "name":"Toxic",
    "type":"Poison",
    "cat":"Status",
    "power":null,
    "acc":90,
    "pp":10,
    "effect":"Badly poisons opponent."
  },
  {
    "name":"Transform",
    "type":"Normal",
    "cat":"Status",
    "power":null,
    "acc":null,
    "pp":10,
    "effect":"User takes on the form and attacks of the opponent."
  },
  {
    "name":"Tri Attack",
    "type":"Normal",
    "cat":"Special",
    "power":80,
    "acc":100,
    "pp":10,
    "effect":"May paralyze, burn or freeze opponent."
  },
  {
    "name":"Twineedle",
    "type":"Bug",
    "cat":"Physical",
    "power":25,
    "acc":100,
    "pp":20,
    "effect":"Hits twice in one turn. May poison opponent."
  },
  {
    "name":"Vice Grip",
    "type":"Normal",
    "cat":"Physical",
    "power":55,
    "acc":100,
    "pp":30,
    "effect":""
  },
  {
    "name":"Vine Whip",
    "type":"Grass",
    "cat":"Physical",
    "power":45,
    "acc":100,
    "pp":25,
    "effect":""
  },
  {
    "name":"Water Gun",
    "type":"Water",
    "cat":"Special",
    "power":40,
    "acc":100,
    "pp":25,
    "effect":""
  },
  {
    "name":"Waterfall",
    "type":"Water",
    "cat":"Physical",
    "power":80,
    "acc":100,
    "pp":15,
    "effect":"May cause flinching."
  },
  {
    "name":"Whirlwind",
    "type":"Normal",
    "cat":"Status",
    "power":null,
    "acc":null,
    "pp":20,
    "effect":"In battles, the opponent switches. In the wild, the Pokémon runs."
  },
  {
    "name":"Wing Attack",
    "type":"Flying",
    "cat":"Physical",
    "power":60,
    "acc":100,
    "pp":35,
    "effect":""
  },
  {
    "name":"Withdraw",
    "type":"Water",
    "cat":"Status",
    "power":null,
    "acc":null,
    "pp":40,
    "effect":"Raises user's Defense."
  },
  {
    "name":"Wrap",
    "type":"Normal",
    "cat":"Physical",
    "power":15,
    "acc":90,
    "pp":20,
    "effect":"Traps opponent, damaging them for 4-5 turns."
  }
]